p_decision_tree/DecisionTree.py
p_decision_tree/__init__.py
p_decision_tree-0.0.3.dist-info/METADATA
p_decision_tree-0.0.3.dist-info/RECORD
p_decision_tree-0.0.3.dist-info/WHEEL
p_decision_tree-0.0.3.dist-info/top_level.txt
