Metadata-Version: 2.1
Name: p-decision-tree
Version: 0.0.3
Summary: Visual Decision Tree Based on Categorical Attributes Package
Home-page: https://github.com/m4jidRafiei/Decision-Tree-Python-
Author: Majid Rafiei
Author-email: majid.rafiei@pads.rwth-aachen.de
License: UNKNOWN
Project-URL: Source, https://github.com/m4jidRafiei/Decision-Tree-Python-
Platform: UNKNOWN
Classifier: Programming Language :: Python :: 3
Classifier: License :: OSI Approved :: MIT License
Classifier: Operating System :: OS Independent
